estonian_e_invoice/__init__.py
estonian_e_invoice/estonian_e_invoice.py
estonian_e_invoice/entities/__init__.py
estonian_e_invoice/entities/account.py
estonian_e_invoice/entities/common.py
estonian_e_invoice/entities/contact.py
estonian_e_invoice/entities/file.py
estonian_e_invoice/entities/invoice.py
estonian_e_invoice/validation/__init__.py
estonian_e_invoice/validation/exceptions.py
estonian_e_invoice/validation/validation_schema_types.py
estonian_e_invoice/validation/validation_schemas.py
estonian_e_invoice/validation/validator_custom_types.py
estonian_e_invoice/validation/validators.py
estonian_e_invoice-1.0.1.dist-info/AUTHORS.rst
estonian_e_invoice-1.0.1.dist-info/LICENSE
estonian_e_invoice-1.0.1.dist-info/METADATA
estonian_e_invoice-1.0.1.dist-info/WHEEL
estonian_e_invoice-1.0.1.dist-info/top_level.txt
estonian_e_invoice-1.0.1.dist-info/RECORD
