Metadata-Version: 2.1
Name: estonian-e-invoice
Version: 1.0.1
Summary: Estonian e-invoice generator
Home-page: https://github.com/thorgate/estonian_e_invoice
Author: Thorgate
Author-email: code@thorgate.eu
License: MIT license
Keywords: estonian_e_invoice
Platform: UNKNOWN
Classifier: Development Status :: 4 - Beta
Classifier: Intended Audience :: Developers
Classifier: License :: OSI Approved :: MIT License
Classifier: Natural Language :: English
Classifier: Programming Language :: Python :: 3
Classifier: Programming Language :: Python :: 3.5
Classifier: Programming Language :: Python :: 3.6
Classifier: Programming Language :: Python :: 3.7
Classifier: Programming Language :: Python :: 3.8
Requires-Python: >=3.5
Requires-Dist: Cerberus (==1.3.2)
